eepackages/__init__.py
eepackages/assets.py
eepackages/geometry.py
eepackages/gl.py
eepackages/tiler.py
eepackages/utils.py
eepackages/applications/__init__.py
eepackages/applications/bathymetry.py
eepackages/applications/waterbody_area.py
eepackages/multiprocessing/__init__.py
eepackages/multiprocessing/download_image.py
eepackages-0.28.0.dist-info/LICENSE
eepackages-0.28.0.dist-info/METADATA
eepackages-0.28.0.dist-info/WHEEL
eepackages-0.28.0.dist-info/top_level.txt
eepackages-0.28.0.dist-info/RECORD
