Metadata-Version: 2.1
Name: eepackages
Version: 0.28.0
Summary: A set of utilities built on top of Google Earth Engine (migrated from JavaScript)
Home-page: https://github.com/gee-community/ee-packages-py
Author: Gennadii Donchyts
Author-email: gennadiy.donchyts@gmail.com
License: MIT
Classifier: Development Status :: 2 - Pre-Alpha
Classifier: License :: OSI Approved :: MIT License
Classifier: Programming Language :: Python
Classifier: Programming Language :: Python :: 2
Classifier: Programming Language :: Python :: 2.7
Classifier: Programming Language :: Python :: 3
Classifier: Programming Language :: Python :: 3.4
Classifier: Programming Language :: Python :: 3.5
Classifier: Programming Language :: Python :: 3.6
Classifier: Programming Language :: Python :: 3.7
License-File: LICENSE
Requires-Dist: earthengine-api >=0.1.284
Requires-Dist: pathos >=0.2.8
Requires-Dist: retry >=0.9.2
